results2web.py
results2web-0.0.1.dist-info/LICENSE
results2web-0.0.1.dist-info/WHEEL
results2web-0.0.1.dist-info/METADATA
results2web-0.0.1.dist-info/RECORD
