Metadata-Version: 2.1
Name: results2web
Version: 0.0.1
Summary: A package to make it easier to go from data analysis to a web delivarable with plots and results. Experimental.
Author-email: Hans Olav Melberg <hans.melberg@gmail.com>
Classifier: License :: OSI Approved :: MIT License
Project-URL: Home, https://results.link
